{"modelName": "HJDQN_2024-01-02T153807", "fileNames": [{"fileName": "HJDQN_2024-01-02T153807_0_0.pth.tar", "avg_reward": -21191.66188056173, "parFileId": 0, "resumeTrainingFlag": null, "Iteration": 0}, {"fileName": "HJDQN_2024-01-02T153807_0_2222.pth.tar", "avg_reward": -24284.771035670594, "parFileId": 0, "resumeTrainingFlag": null, "Iteration": 2222}, {"fileName": "HJDQN_2024-01-02T153807_0_4444.pth.tar", "avg_reward": -25054.22566555281, "parFileId": 0, "resumeTrainingFlag": null, "Iteration": 4444}, {"fileName": "HJDQN_2024-01-02T153807_0_6666.pth.tar", "avg_reward": -24300.49821832209, "parFileId": 0, "resumeTrainingFlag": null, "Iteration": 6666}, {"fileName": "HJDQN_2024-01-02T153807_0_8888.pth.tar", "avg_reward": -24077.565169408495, "parFileId": 0, "resumeTrainingFlag": null, "Iteration": 8888}, {"fileName": "HJDQN_2024-01-02T153807_0_11110.pth.tar", "avg_reward": -24278.817901139697, "parFileId": 0, "resumeTrainingFlag": null, "Iteration": 11110}, {"fileName": "HJDQN_2024-01-02T153807_0_13332.pth.tar", "avg_reward": -24364.835749218524, "parFileId": 0, "resumeTrainingFlag": null, "Iteration": 13332}, {"fileName": "HJDQN_2024-01-02T153807_0_15554.pth.tar", "avg_reward": -23991.06731313812, "parFileId": 0, "resumeTrainingFlag": null, "Iteration": 15554}, {"fileName": "HJDQN_2024-01-02T153807_0_17776.pth.tar", "avg_reward": -24263.436134341155, "parFileId": 0, "resumeTrainingFlag": null, "Iteration": 17776}, {"fileName": "HJDQN_2024-01-02T153807_0_19998.pth.tar", "avg_reward": -24218.07216691122, "parFileId": 0, "resumeTrainingFlag": null, "Iteration": 19998}]}